pypynum/PyPyNum.png
pypynum/README.md
pypynum/__init__.py
pypynum/arrays.py
pypynum/chars.py
pypynum/ciphers.py
pypynum/consts.py
pypynum/crandom.py
pypynum/dataproc.py
pypynum/dists.py
pypynum/equations.py
pypynum/fft.py
pypynum/files.py
pypynum/geoms.py
pypynum/graphs.py
pypynum/groups.py
pypynum/hypcmpnms.py
pypynum/images.py
pypynum/interp.py
pypynum/kernels.py
pypynum/logics.py
pypynum/maths.py
pypynum/matrices.py
pypynum/multiprec.py
pypynum/networks.py
pypynum/numbers.py
pypynum/plotting.py
pypynum/polys.py
pypynum/pprinters.py
pypynum/random.py
pypynum/regs.py
pypynum/seqs.py
pypynum/special.py
pypynum/stattest.py
pypynum/symbols.py
pypynum/tensors.py
pypynum/test.py
pypynum/this.py
pypynum/tools.py
pypynum/trees.py
pypynum/types.py
pypynum/ufuncs.py
pypynum/utils.py
pypynum/vectors.py
pypynum/zh_cn.py
PyPyNum-1.17.2.dist-info/METADATA
PyPyNum-1.17.2.dist-info/WHEEL
PyPyNum-1.17.2.dist-info/top_level.txt
PyPyNum-1.17.2.dist-info/RECORD
